odoo/addons/ssi_odoo_implementation_work_log/README.rst
odoo/addons/ssi_odoo_implementation_work_log/__init__.py
odoo/addons/ssi_odoo_implementation_work_log/__manifest__.py
odoo/addons/ssi_odoo_implementation_work_log/i18n/ssi_odoo_implementation_work_log.pot
odoo/addons/ssi_odoo_implementation_work_log/models/__init__.py
odoo/addons/ssi_odoo_implementation_work_log/models/odoo_change_request.py
odoo/addons/ssi_odoo_implementation_work_log/models/odoo_configuration_change_record.py
odoo/addons/ssi_odoo_implementation_work_log/models/odoo_deployment.py
odoo/addons/ssi_odoo_implementation_work_log/models/odoo_feature_implementation.py
odoo/addons/ssi_odoo_implementation_work_log/models/odoo_feature_issue.py
odoo/addons/ssi_odoo_implementation_work_log/models/odoo_implementation.py
odoo/addons/ssi_odoo_implementation_work_log/models/odoo_use_case_specification.py
odoo/addons/ssi_odoo_implementation_work_log/static/description/icon.png
odoo14_addon_ssi_odoo_implementation_work_log-14.0.1.4.0.dist-info/METADATA
odoo14_addon_ssi_odoo_implementation_work_log-14.0.1.4.0.dist-info/WHEEL
odoo14_addon_ssi_odoo_implementation_work_log-14.0.1.4.0.dist-info/top_level.txt
odoo14_addon_ssi_odoo_implementation_work_log-14.0.1.4.0.dist-info/RECORD
